erh/__init__.py
erh/client.py
erh/analysis/__init__.py
erh/analysis/baseline_comparison.py
erh/analysis/edge_cases.py
erh/analysis/erh_checks.py
erh/analysis/fluid_model.py
erh/analysis/opinion_dynamics.py
erh/analysis/statistics.py
erh/analysis/temporal_analysis.py
erh/analysis/zeta_function.py
erh/analysis/zeta_zeros_analysis.py
erh/core/__init__.py
erh/core/abm_simulator.py
erh/core/action_space.py
erh/core/adaptive_threshold.py
erh/core/agent.py
erh/core/axioms.py
erh/core/ethical_primes.py
erh/core/fuzzy_judgment.py
erh/core/hybrid_model.py
erh/core/judgement_system.py
erh/core/meta_monitor.py
erh/core/output_writer.py
erh/core/prime_dependency_graph.py
erh/core/probabilistic_values.py
erh/core/social_network.py
erh/core/temporal_erh.py
erh/tools/__init__.py
erh/tools/aif360_adapter.py
erh/tools/art_adapter.py
erh/tools/pipeline.py
erh-0.1.0.dist-info/METADATA
erh-0.1.0.dist-info/WHEEL
erh-0.1.0.dist-info/top_level.txt
erh-0.1.0.dist-info/RECORD
