Metadata-Version: 2.4
Name: erh
Version: 0.1.0
Summary: Ethical Riemann Hypothesis (ERH) Simulation SDK
Author-email: Ethical AI Research Team <contact@ethical-ai.org>
Project-URL: Homepage, https://github.com/dennislee928/Ethic-Latex
Project-URL: Bug Tracker, https://github.com/dennislee928/Ethic-Latex/issues
Classifier: Programming Language :: Python :: 3
Classifier: License :: OSI Approved :: MIT License
Classifier: Operating System :: OS Independent
Requires-Python: >=3.10
Requires-Dist: numpy>=1.20.0
Requires-Dist: scipy>=1.7.0
Requires-Dist: pandas>=1.3.0
Requires-Dist: matplotlib>=3.4.0
Requires-Dist: fastapi>=0.95.0
Requires-Dist: httpx>=0.24.0
Requires-Dist: requests>=2.28.0
Provides-Extra: ml
Requires-Dist: adversarial-robustness-toolbox>=1.14.0; extra == "ml"
Requires-Dist: aif360>=0.5.0; extra == "ml"
Requires-Dist: scikit-learn>=1.0.0; extra == "ml"
